ansprogen
