Metadata-Version: 1.0
Name: ansprogen
Version: 0.0.5
Summary: A project generator tools for easy create project skeleton.
Home-page: http://www.mindtalk.com/u/anvie
Author: Robin Syihab
Author-email: r[@]nosql.asia
License: MIT
Download-URL: https://github.com/anvie/Ansprogen
Keywords: ansprogen project generator
Platform: UNKNOWN
Classifier: Development Status :: 3 - Alpha
Classifier: Topic :: Utilities
Classifier: License :: OSI Approved :: MIT License
